schickit/__init__.py
schickit/main.py
schickit/utils/Generate_scNanoHIC_pairs.py
schickit/utils/ReformSAM.py
schickit/utils/__init__.py
schickit/utils/_version.py
schickit/utils/analysis.py
schickit/utils/assembly.py
schickit/utils/correct.py
schickit/utils/download.py
schickit/utils/embedding.py
schickit/utils/general.py
schickit/utils/help.py
schickit/utils/hicCorrectMatrix.py
schickit/utils/iterativeCorrection.py
schickit/utils/plot.py
schickit/utils/scNano.py
schickit/utils/scNano_barcode.py
schickit/utils/scSPRITE.py
schickit/utils/scaffold.py
schickit/utils/sciHic.py
schickit/utils/sn_m3c.py
schickit/utils/tools.py
schickit/utils/utilities.py
schickit/utils/visualize.py
schickit-0.0.59.dist-info/METADATA
schickit-0.0.59.dist-info/WHEEL
schickit-0.0.59.dist-info/entry_points.txt
schickit-0.0.59.dist-info/top_level.txt
schickit-0.0.59.dist-info/RECORD
