Metadata-Version: 2.1
Name: schickit
Version: 0.0.59
Summary: a toolkit for processing single cell Hi-C data
Author: ABC
Requires-Dist: numpy
Requires-Dist: pandas (<2,>=1.5.1)
Requires-Dist: cython
Requires-Dist: cmake
Requires-Dist: pysam
Requires-Dist: pairtools (>=0.3.3)
Requires-Dist: bioframe (>=0.4.1)
Requires-Dist: anndata (>=0.9.2)
Requires-Dist: cached-property (>=1.5.2)
Requires-Dist: chart-studio (>=1.1.0)
Requires-Dist: cleanlab (>=2.4.0)
Requires-Dist: click (>=8.1.6)
Requires-Dist: cloudpickle (>=2.2.1)
Requires-Dist: cooler (>=0.9.2)
Requires-Dist: h5py (>=3.7.0)
Requires-Dist: igraph (>=0.10.6)
Requires-Dist: leidenalg (>=0.10.0)
Requires-Dist: Levenshtein (>=0.21.1)
Requires-Dist: markdown-it-py (>=3.0.0)
Requires-Dist: MarkupSafe (>=2.1.3)
Requires-Dist: matplotlib (>=3.5.3)
Requires-Dist: numba (>=0.57.1)
Requires-Dist: scipy (>=1.7.0)
Requires-Dist: pandas (>=1.3.4)
Requires-Dist: pyyaml
Requires-Dist: bioframe (>=0.3.3)
Requires-Dist: pysam (>=0.15.0)
Requires-Dist: cooltools
Requires-Dist: pyBigWig (>=0.3.22)
Requires-Dist: PyYAML (>=6.0.1)
Requires-Dist: scikit-learn (>=1.1.2)
Requires-Dist: scipy (>=1.9.3)
Requires-Dist: seaborn (>=0.12.2)
Requires-Dist: tornado
Requires-Dist: tqdm (>=4.65.0)
Requires-Dist: umap-learn (>=0.5.3)
Requires-Dist: hicmatrix (>=17)
Requires-Dist: unidecode (>=1.3.6)
Requires-Dist: krbalancing
Requires-Dist: scanpy (>=1.9.4)
